mini_mlflow/__init__.py
mini_mlflow/run.py
mini_mlflow/storage.py
mini_mlflow/tracker.py
mini_mlflow-0.1.0.dist-info/licenses/LICENSE
mini_mlflow-0.1.0.dist-info/METADATA
mini_mlflow-0.1.0.dist-info/WHEEL
mini_mlflow-0.1.0.dist-info/top_level.txt
mini_mlflow-0.1.0.dist-info/RECORD
