Metadata-Version: 2.4
Name: mini-mlflow
Version: 0.1.0
Summary: A minimal ML experiment tracker
Author: Mini MLflow Contributors
License: MIT
Project-URL: Homepage, https://github.com/yourusername/mini-mlflow
Project-URL: Documentation, https://github.com/yourusername/mini-mlflow#readme
Project-URL: Repository, https://github.com/yourusername/mini-mlflow
Project-URL: Issues, https://github.com/yourusername/mini-mlflow/issues
Keywords: mlflow,machine-learning,experiment-tracking,ml,tracking
Classifier: Development Status :: 4 - Beta
Classifier: Intended Audience :: Developers
Classifier: Intended Audience :: Science/Research
Classifier: License :: OSI Approved :: MIT License
Classifier: Programming Language :: Python :: 3
Classifier: Programming Language :: Python :: 3.7
Classifier: Programming Language :: Python :: 3.8
Classifier: Programming Language :: Python :: 3.9
Classifier: Programming Language :: Python :: 3.10
Classifier: Programming Language :: Python :: 3.11
Classifier: Topic :: Scientific/Engineering :: Artificial Intelligence
Classifier: Topic :: Software Development :: Libraries :: Python Modules
Requires-Python: >=3.7
License-File: LICENSE
Requires-Dist: pyyaml>=5.1
Provides-Extra: dev
Requires-Dist: pytest>=6.0; extra == "dev"
Requires-Dist: pytest-cov>=2.0; extra == "dev"
Dynamic: license-file
Dynamic: requires-python
